do_app_sandbox/__init__.py
do_app_sandbox/__main__.py
do_app_sandbox/async_sandbox.py
do_app_sandbox/cli.py
do_app_sandbox/deployer.py
do_app_sandbox/exceptions.py
do_app_sandbox/executor.py
do_app_sandbox/filesystem.py
do_app_sandbox/image_registry.py
do_app_sandbox/image_validator.py
do_app_sandbox/process.py
do_app_sandbox/sandbox.py
do_app_sandbox/spaces.py
do_app_sandbox/types.py
do_app_sandbox-0.1.2.dist-info/METADATA
do_app_sandbox-0.1.2.dist-info/WHEEL
do_app_sandbox-0.1.2.dist-info/entry_points.txt
do_app_sandbox-0.1.2.dist-info/licenses/LICENSE
do_app_sandbox-0.1.2.dist-info/RECORD
