Metadata-Version: 2.4
Name: do-app-sandbox
Version: 0.1.2
Summary: Experimental sandbox API for DigitalOcean App Platform - provides sandbox-like capabilities similar to Cloudflare Sandbox
Project-URL: Homepage, https://github.com/bikramkgupta/do-app-sandbox
Project-URL: Documentation, https://github.com/bikramkgupta/do-app-sandbox#readme
Project-URL: Repository, https://github.com/bikramkgupta/do-app-sandbox
Project-URL: Issues, https://github.com/bikramkgupta/do-app-sandbox/issues
Author-email: Bikram Gupta <bikram.gupta@gmail.com>
License: MIT
License-File: LICENSE
Keywords: app-platform,cloud,containers,digitalocean,sandbox
Classifier: Development Status :: 3 - Alpha
Classifier: Intended Audience :: Developers
Classifier: License :: OSI Approved :: MIT License
Classifier: Operating System :: OS Independent
Classifier: Programming Language :: Python :: 3
Classifier: Programming Language :: Python :: 3.10
Classifier: Programming Language :: Python :: 3.11
Classifier: Programming Language :: Python :: 3.12
Classifier: Programming Language :: Python :: 3.13
Classifier: Topic :: Software Development :: Libraries :: Python Modules
Requires-Python: >=3.10.12
Requires-Dist: pexpect>=4.9.0
Provides-Extra: all
Requires-Dist: boto3>=1.34.0; extra == 'all'
Provides-Extra: dev
Requires-Dist: pytest>=8.0.0; extra == 'dev'
Provides-Extra: spaces
Requires-Dist: boto3>=1.34.0; extra == 'spaces'
